LICENSE
MANIFEST.in
README.md
setup.py
mkdocs_glightbox/__init__.py
mkdocs_glightbox/plugin.py
mkdocs_glightbox/glightbox/LICENSE.md
mkdocs_glightbox/glightbox/glightbox.min.css
mkdocs_glightbox/glightbox/glightbox.min.js
mkdocs_glightbox_tables.egg-info/PKG-INFO
mkdocs_glightbox_tables.egg-info/SOURCES.txt
mkdocs_glightbox_tables.egg-info/dependency_links.txt
mkdocs_glightbox_tables.egg-info/entry_points.txt
mkdocs_glightbox_tables.egg-info/requires.txt
mkdocs_glightbox_tables.egg-info/top_level.txt