Metadata-Version: 2.1
Name: mkdocs-glightbox-tables
Version: 0.2.4
Summary: MkDocs plugin supports image and table lightbox with GLightbox.
Author: ThomasPJ
License: MIT
Keywords: mkdocs,plugin,lightbox
License-File: LICENSE
Requires-Dist: beautifulsoup4>=4.11.1
